pysilence/__init__.py
pysilence/silence.py
pysilence/util.py
pysilence/window.py
pysilence/test/__init__.py
pysilence/test/iterator_queue_unittest.py
pysilence/test/iterator_unittest.py
pysilence-0.1.3.dist-info/LICENCE
pysilence-0.1.3.dist-info/METADATA
pysilence-0.1.3.dist-info/WHEEL
pysilence-0.1.3.dist-info/top_level.txt
pysilence-0.1.3.dist-info/RECORD
