Metadata-Version: 2.1
Name: pysilence
Version: 0.1.3
Summary: A silence detection module
Home-page: https://github.com/antonbaumann/pysilence
Author: Anton Baumann
Author-email: anton@antonbaumann.com
License: UNKNOWN
Platform: UNKNOWN
Classifier: Programming Language :: Python :: 3
Classifier: License :: OSI Approved :: MIT License
Classifier: Operating System :: OS Independent
